Auria/Signature.py
Auria/SignedTransaction.py
Auria/Transaction.py
Auria/Wallet.py
Auria/__init__.py
auria-1.0.1.dist-info/licenses/LICENSE
auria-1.0.1.dist-info/METADATA
auria-1.0.1.dist-info/WHEEL
auria-1.0.1.dist-info/top_level.txt
auria-1.0.1.dist-info/RECORD
